<?xml version="1.0" encoding="UTF-8"?>
<schemalist>
  <schema id="org.fedoraproject.fedmsg.notify" path="/org/fedoraproject/fedmsg/notify/">
    <key type="b" name="enabled">
      <default>true</default>
      <summary>fedmsg-notify service enabled</summary>
      <description>Whether or not the fedmsg-notify service should be running</description>
    </key>
    <key type="s" name="enabled-filters">
      <default>''</default>
      <summary>a list of enabled fedmsg-notify filters</summary>
      <description>A space delimeted string of fedmsg-notify filters names that are enabled</description>
    </key>
    <key type="b" name="emit-dbus-signals">
      <default>false</default>
      <summary>Emit signals for each message</summary>
      <description>This tells fedmsg-notify to emit a DBus signal for each message received from fedmsg. This allows desktop applications to consume messages without each having seperate connections to the bus.</description>
    </key>
    <key type="s" name="filter-settings">
      <default>'{}'</default>
      <summary>User configured filter settings</summary>
      <description>A JSON dictionary of advanced filter settings.</description>
    </key>
    <key type="i" name="max-notifications">
      <default>100</default>
      <summary>The maximum number of notifications to keep open</summary>
      <description>Defines how many notifications to keep open at once.</description>
    </key>
    <key type="s" name="topic">
      <default>'org.fedoraproject.*'</default>
      <summary>The prefix of the topics we want to listen to</summary>
      <description>The prefix of the topics we want to get notified for.</description>
    </key>
    <key type="i" name="expiration">
      <default>0</default>
      <summary>The default expiration of all notifications</summary>
      <description>Defines how many seconds to display each notification. The default is 0, which causes them to never expire.</description>
    </key>
  </schema>
</schemalist>
